mcp_todoist_organizer/__init__.py
mcp_todoist_organizer/server.py
mcp_todoist_organizer-0.0.2.dist-info/METADATA
mcp_todoist_organizer-0.0.2.dist-info/WHEEL
mcp_todoist_organizer-0.0.2.dist-info/entry_points.txt
mcp_todoist_organizer-0.0.2.dist-info/top_level.txt
mcp_todoist_organizer-0.0.2.dist-info/RECORD
